odoo8_addon_stock_cycle_count-8.0.1.2.0.99.dev9-py3.8-nspkg.pth
odoo_addons/stock_cycle_count/README.rst
odoo_addons/stock_cycle_count/__init__.py
odoo_addons/stock_cycle_count/__openerp__.py
odoo_addons/stock_cycle_count/data/cycle_count_ir_cron.xml
odoo_addons/stock_cycle_count/data/cycle_count_sequence.xml
odoo_addons/stock_cycle_count/i18n/am.po
odoo_addons/stock_cycle_count/i18n/ar.po
odoo_addons/stock_cycle_count/i18n/bg.po
odoo_addons/stock_cycle_count/i18n/bs.po
odoo_addons/stock_cycle_count/i18n/ca.po
odoo_addons/stock_cycle_count/i18n/ca_ES.po
odoo_addons/stock_cycle_count/i18n/cs.po
odoo_addons/stock_cycle_count/i18n/da.po
odoo_addons/stock_cycle_count/i18n/de.po
odoo_addons/stock_cycle_count/i18n/el_GR.po
odoo_addons/stock_cycle_count/i18n/en_AU.po
odoo_addons/stock_cycle_count/i18n/en_GB.po
odoo_addons/stock_cycle_count/i18n/es.po
odoo_addons/stock_cycle_count/i18n/es_AR.po
odoo_addons/stock_cycle_count/i18n/es_CL.po
odoo_addons/stock_cycle_count/i18n/es_CO.po
odoo_addons/stock_cycle_count/i18n/es_CR.po
odoo_addons/stock_cycle_count/i18n/es_DO.po
odoo_addons/stock_cycle_count/i18n/es_EC.po
odoo_addons/stock_cycle_count/i18n/es_ES.po
odoo_addons/stock_cycle_count/i18n/es_MX.po
odoo_addons/stock_cycle_count/i18n/es_PE.po
odoo_addons/stock_cycle_count/i18n/es_PY.po
odoo_addons/stock_cycle_count/i18n/es_VE.po
odoo_addons/stock_cycle_count/i18n/et.po
odoo_addons/stock_cycle_count/i18n/eu.po
odoo_addons/stock_cycle_count/i18n/fa.po
odoo_addons/stock_cycle_count/i18n/fi.po
odoo_addons/stock_cycle_count/i18n/fr.po
odoo_addons/stock_cycle_count/i18n/fr_CA.po
odoo_addons/stock_cycle_count/i18n/fr_CH.po
odoo_addons/stock_cycle_count/i18n/fr_FR.po
odoo_addons/stock_cycle_count/i18n/gl.po
odoo_addons/stock_cycle_count/i18n/gl_ES.po
odoo_addons/stock_cycle_count/i18n/he.po
odoo_addons/stock_cycle_count/i18n/hi.po
odoo_addons/stock_cycle_count/i18n/hr.po
odoo_addons/stock_cycle_count/i18n/hr_HR.po
odoo_addons/stock_cycle_count/i18n/hu.po
odoo8_addon_stock_cycle_count-8.0.1.2.0.99.dev9.dist-info/METADATA
odoo8_addon_stock_cycle_count-8.0.1.2.0.99.dev9.dist-info/WHEEL
odoo8_addon_stock_cycle_count-8.0.1.2.0.99.dev9.dist-info/namespace_packages.txt
odoo8_addon_stock_cycle_count-8.0.1.2.0.99.dev9.dist-info/top_level.txt
odoo8_addon_stock_cycle_count-8.0.1.2.0.99.dev9.dist-info/RECORD
